obstruction/__init__.py
obstruction-0.1.1.dist-info/DESCRIPTION.rst
obstruction-0.1.1.dist-info/METADATA
obstruction-0.1.1.dist-info/RECORD
obstruction-0.1.1.dist-info/WHEEL
obstruction-0.1.1.dist-info/metadata.json
obstruction-0.1.1.dist-info/top_level.txt
